{
  "week": 102,
  "theme": "ビートルズのカバー曲で漫遊記",
  "date": "2019-12-15T00:00:00.000Z",
  "playlist": [
    {
      "id": 844,
      "week": 102,
      "name": "空も飛べるはず (Album Version)",
      "artist": "スピッツ",
      "kana": "",
      "year": 1994,
      "nation": "JPN",
      "label": "ポリドール",
      "producer": "笹路正徳",
      "corner": "漫遊前の一曲",
      "youtube": "h-kQw4JqCHE"
    },
    {
      "id": 845,
      "week": 102,
      "name": "キャント・バイ・ミー・ラブ",
      "artist": "東京ビートルズ",
      "kana": "とうきょうびーとるず",
      "year": 1964,
      "nation": "JPN",
      "label": "ビクターエンタテイメント",
      "producer": "",
      "corner": "",
      "youtube": ""
    },
    {
      "id": 846,
      "week": 102,
      "name": "Day Tripper",
      "artist": "Cheap Trick",
      "kana": "",
      "year": 1980,
      "nation": "US",
      "label": "Epic",
      "producer": "",
      "corner": "",
      "youtube": "aWz3pM0j90M"
    },
    {
      "id": 847,
      "week": 102,
      "name": "We Can Work It Out",
      "artist": "Deep Purple",
      "kana": "",
      "year": 1969,
      "nation": "UK",
      "label": "Harvest",
      "producer": "Derek Lawrence",
      "corner": "",
      "youtube": "UY1C_Hn6Sdo"
    },
    {
      "id": 848,
      "week": 102,
      "name": "イエロー・サブマリン音頭",
      "artist": "金沢明子",
      "kana": "かなざわあきこ",
      "year": 1982,
      "nation": "JPN",
      "label": "ビクター",
      "producer": "大瀧詠一",
      "corner": "",
      "youtube": ""
    },
    {
      "id": 849,
      "week": 102,
      "name": "Helier Skelter",
      "artist": "Mötley Crüe",
      "kana": "",
      "year": 1983,
      "nation": "US",
      "label": "Elektra",
      "producer": "Tom Werman",
      "corner": "",
      "youtube": "_QrBJNtC-MU"
    },
    {
      "id": 850,
      "week": 102,
      "name": "I’ve Just Seen A Face",
      "artist": "小野リサ",
      "kana": "おのりさ",
      "year": 2006,
      "nation": "JPN",
      "label": "東芝EMI",
      "producer": "",
      "corner": "",
      "youtube": "XBaTkoWhVBA"
    },
    {
      "id": 851,
      "week": 102,
      "name": "Across the Universe",
      "artist": "Fiona Apple",
      "kana": "",
      "year": 1998,
      "nation": "US",
      "label": "New Line Records",
      "producer": "",
      "corner": "",
      "youtube": ""
    },
    {
      "id": 852,
      "week": 102,
      "name": "あなたはやって来る 〜Dear Santa〜",
      "artist": "小谷美紗子",
      "kana": "おだにみさこ",
      "year": 1997,
      "nation": "JPN",
      "label": "ユニバーサル",
      "producer": "",
      "corner": "ちょっぴりタイムマシン",
      "youtube": ""
    }
  ]
}